systemmonitoringcenter/__init__.py
systemmonitoringcenter/start.py
systemmonitoringcenter/database/20-sdio-vendor-model.hwdb
systemmonitoringcenter/database/arm.ids
systemmonitoringcenter/database/database_license.txt
systemmonitoringcenter/database/sdcard.ids
systemmonitoringcenter/icons/hicolor/scalable/actions/system-monitoring-center-cpu-symbolic.svg
systemmonitoringcenter/icons/hicolor/scalable/actions/system-monitoring-center-disk-hdd-symbolic.svg
systemmonitoringcenter/icons/hicolor/scalable/actions/system-monitoring-center-fan-symbolic.svg
systemmonitoringcenter/icons/hicolor/scalable/actions/system-monitoring-center-graphics-card-symbolic.svg
systemmonitoringcenter/icons/hicolor/scalable/actions/system-monitoring-center-network-symbolic.svg
systemmonitoringcenter/icons/hicolor/scalable/actions/system-monitoring-center-performance-symbolic.svg
systemmonitoringcenter/icons/hicolor/scalable/actions/system-monitoring-center-process-symbolic.svg
systemmonitoringcenter/icons/hicolor/scalable/actions/system-monitoring-center-ram-symbolic.svg
systemmonitoringcenter/icons/hicolor/scalable/actions/system-monitoring-center-services-symbolic.svg
systemmonitoringcenter/icons/hicolor/scalable/actions/system-monitoring-center-system-symbolic.svg
systemmonitoringcenter/icons/hicolor/scalable/actions/system-monitoring-center-temperature-symbolic.svg
systemmonitoringcenter/icons/hicolor/scalable/actions/system-monitoring-center-user-symbolic.svg
systemmonitoringcenter/icons/hicolor/scalable/actions/system-monitoring-center-voltage-symbolic.svg
systemmonitoringcenter/icons/hicolor/scalable/apps/system-monitoring-center.svg
systemmonitoringcenter/integration/io.github.hakandundar34coding.system-monitoring-center.desktop
systemmonitoringcenter/locale/cs/LC_MESSAGES/system-monitoring-center.mo
systemmonitoringcenter/locale/de/LC_MESSAGES/system-monitoring-center.mo
systemmonitoringcenter/locale/es/LC_MESSAGES/system-monitoring-center.mo
system_monitoring_center-1.42.0.dist-info/LICENSE
system_monitoring_center-1.42.0.dist-info/METADATA
system_monitoring_center-1.42.0.dist-info/WHEEL
system_monitoring_center-1.42.0.dist-info/entry_points.txt
system_monitoring_center-1.42.0.dist-info/top_level.txt
system_monitoring_center-1.42.0.dist-info/RECORD
