Metadata-Version: 2.1
Name: system-monitoring-center
Version: 1.42.0
Summary: Multi-featured system monitor
Home-page: https://github.com/hakandundar34coding/system-monitoring-center
Author: Hakan Dündar
Author-email: hakandundar34coding@gmail.com
License: GPLv3
Keywords: system monitor task manager performance cpu ram swap memory disk network gpu processes users services
Classifier: Programming Language :: Python :: 3 :: Only
Classifier: Programming Language :: Python :: 3
Classifier: Programming Language :: Python :: 3.6
Classifier: Programming Language :: Python :: 3.7
Classifier: Programming Language :: Python :: 3.8
Classifier: Programming Language :: Python :: 3.9
Classifier: Programming Language :: Python :: 3.10
Classifier: Programming Language :: Python :: 3.11
Classifier: Programming Language :: Python :: 3.12
Classifier: License :: OSI Approved :: GNU General Public License v3 (GPLv3)
Classifier: Operating System :: POSIX :: Linux
Classifier: Topic :: System :: Monitoring
Requires-Python: >=3.6
License-File: LICENSE
Requires-Dist: PyGObject
Requires-Dist: pycairo
